setup.py
SubhoDataStructure/__init__.py
SubhoDataStructure/binary_tree.py
SubhoDataStructure/test_tree.py
SubhoDataStructure.egg-info/PKG-INFO
SubhoDataStructure.egg-info/SOURCES.txt
SubhoDataStructure.egg-info/dependency_links.txt
SubhoDataStructure.egg-info/top_level.txt