Metadata-Version: 1.0
Name: SubhoDataStructure
Version: 1.1
Summary: Common data structures for python. Now it only contain binary tree but in future updates more data structures will be added.
Home-page: https://github.com/SubhoBasak
Author: Subho Basak
Author-email: subhobasak50@gmail.com
License: Open Source
Platform: UNKNOWN
